hot_tool/__init__.py
hot_tool/_hot_tool.py
hot_tool/cli.py
hot_tool/exceptions.py
hot_tool/run.py
hot_tool-0.0.5.dist-info/METADATA
hot_tool-0.0.5.dist-info/WHEEL
hot_tool-0.0.5.dist-info/entry_points.txt
hot_tool-0.0.5.dist-info/licenses/LICENSE
hot_tool-0.0.5.dist-info/RECORD
