Metadata-Version: 2.4
Name: hot-tool
Version: 0.0.5
Summary: Build and package Python tools into standalone executables for LLM integration.
License: MIT
License-File: LICENSE
Author: Allen Chou
Author-email: f1470891079@gmail.com
Requires-Python: >=3.11,<4
Classifier: License :: OSI Approved :: MIT License
Classifier: Programming Language :: Python :: 3
Classifier: Programming Language :: Python :: 3.11
Classifier: Programming Language :: Python :: 3.12
Classifier: Programming Language :: Python :: 3.13
Classifier: Programming Language :: Python :: 3.14
Provides-Extra: all
Project-URL: Homepage, https://github.com/allen2c/hot-tool
Project-URL: PyPI, https://pypi.org/project/hot-tool/
Project-URL: Repository, https://github.com/allen2c/hot-tool
